ber_tlv_decoder-0.1.1.dist-info/METADATA
ber_tlv_decoder-0.1.1.dist-info/WHEEL
ber_tlv_decoder-0.1.1.dist-info/licenses/LICENSE
ber_tlv_decoder/__init__.py
ber_tlv_decoder/ber_tlv_decoder.cpython-310-i386-linux-gnu.so
ber_tlv_decoder-0.1.1.dist-info/RECORD
