Metadata-Version: 2.4
Name: ber_tlv_decoder
Version: 0.1.1
Classifier: Programming Language :: Rust
Classifier: Programming Language :: Python :: Implementation :: CPython
Classifier: Programming Language :: Python :: Implementation :: PyPy
Requires-Dist: maturin>=1.8.3
License-File: LICENSE
Author-email: Matheus Cafalchio <mcafalchio@gmail.com>
Requires-Python: >=3.8
